README.md
broxus_api_client/__init__.py
broxus_api_client/base_client.py
broxus_api_client/base_model.py
broxus_api_client/constants.py
broxus_api_client/errors.py
broxus_api_client/explorer/__init__.py
broxus_api_client/explorer/client.py
broxus_api_client/explorer/models.py
broxus_api_client/token_indexer/__init__.py
broxus_api_client/token_indexer/client.py
broxus_api_client/token_indexer/models.py
broxus_api_client-0.1.0.dist-info/LICENSE
broxus_api_client-0.1.0.dist-info/WHEEL
broxus_api_client-0.1.0.dist-info/METADATA
broxus_api_client-0.1.0.dist-info/RECORD
