Metadata-Version: 2.1
Name: broxus-api-client
Version: 0.1.0
Summary: Set of API clients for Broxus APIs in Everscale
Home-page: https://github.com/MIREX/broxus_api_client
License: MIT
Author: MIREX
Author-email: lifincevkirill@gmail.com
Requires-Python: >=3.9,<4.0
Classifier: Framework :: AsyncIO
Classifier: License :: OSI Approved :: MIT License
Classifier: Operating System :: OS Independent
Classifier: Programming Language :: Python :: 3
Classifier: Programming Language :: Python :: 3.10
Classifier: Programming Language :: Python :: 3.9
Classifier: Topic :: Software Development :: Libraries :: Python Modules
Classifier: Typing :: Typed
Requires-Dist: httpx[http2] (>=0.22.0,<0.23.0)
Requires-Dist: pydantic (>=1.9.0,<2.0.0)
Requires-Dist: ujson (>=5.1.0,<6.0.0)
Project-URL: Repository, https://github.com/MIREX/broxus_api_client
